cutility/__init__.py
cutility/path_manager.py
cutility/cleaners/__init__.py
cutility/cleaners/clean.py
cutility/cleaners/pii_cleaner.py
cutility/cleaners/text_cleaner.py
cutility/io/__init__.py
cutility/io/readers/__init__.py
cutility/io/readers/_json_reader.py
cutility/io/readers/_jsonl_reader.py
cutility/io/readers/_text_reader.py
cutility/io/readers/_yaml_reader.py
cutility/io/writers/__init__.py
cutility/io/writers/_json_writer.py
cutility/io/writers/_jsonl_writer.py
cutility/io/writers/_text_writer.py
cutility/io/writers/_yaml_writer.py
cutility/loggers/__init__.py
cutility/loggers/_simple_logger.py
cutility/utils/__init__.py
cutility/utils/env_loader.py
cutility/utils/exec_time.py
cutility/utils/path.py
cutility-1.0.1.dist-info/LICENSE
cutility-1.0.1.dist-info/METADATA
cutility-1.0.1.dist-info/WHEEL
cutility-1.0.1.dist-info/top_level.txt
cutility-1.0.1.dist-info/RECORD
