Metadata-Version: 2.1
Name: cutility
Version: 1.0.1
Summary: Common Utility functions for development
Home-page: https://github.com/sagarshq/cutility
Author: Sagar Sarkale
Author-email: sagarsarkale.work@gmail.com
Classifier: Programming Language :: Python :: 3
Classifier: License :: OSI Approved :: MIT License
Classifier: Operating System :: OS Independent
Classifier: Topic :: Utilities
Requires-Python: >=3.7
License-File: LICENSE
Requires-Dist: simplejson
Requires-Dist: pyyaml
Requires-Dist: python-dotenv
